codemod_json/__init__.py
codemod_json/_version.py
codemod_json/base.py
codemod_json/items.py
codemod_json/parser.py
codemod_json/py.typed
codemod_json/style.py
codemod_json/util.py
codemod_json-0.5.1.dist-info/LICENSE
codemod_json-0.5.1.dist-info/METADATA
codemod_json-0.5.1.dist-info/WHEEL
codemod_json-0.5.1.dist-info/top_level.txt
codemod_json-0.5.1.dist-info/RECORD
