Metadata-Version: 2.1
Name: codemod-json
Version: 0.5.1
Summary: Lib to modify json inplace
Home-page: https://github.com/advice-animal/codemod-json/
Author: Tim Hatch
Author-email: tim@timhatch.com
License: MIT
Requires-Python: >=3.9
License-File: LICENSE
Requires-Dist: tree-sitter>=0.23.2
Requires-Dist: tree-sitter-json>=0.24.8
Provides-Extra: dev
Requires-Dist: ruff==0.8.0; extra == "dev"
Requires-Dist: checkdeps==0.9.0; extra == "dev"
Requires-Dist: mypy==1.13.0; extra == "dev"
Requires-Dist: tox==4.23.2; extra == "dev"
Provides-Extra: test
Requires-Dist: coverage>=6; extra == "test"
Requires-Dist: pytest; extra == "test"
Requires-Dist: pytest-cov; extra == "test"
Requires-Dist: moreorless; extra == "test"
